cdxev/__init__.py
cdxev/__main__.py
cdxev/build_public_bom.py
cdxev/error.py
cdxev/initialize_sbom.py
cdxev/list_command.py
cdxev/log.py
cdxev/merge.py
cdxev/pkg.py
cdxev/set.py
cdxev/vex.py
cdxev/amend/__init__.py
cdxev/amend/command.py
cdxev/amend/license.py
cdxev/amend/license_name_spdx_id_map.json
cdxev/amend/operations.py
cdxev/auxiliary/__init__.py
cdxev/auxiliary/filename_gen.py
cdxev/auxiliary/identity.py
cdxev/auxiliary/io_processing.py
cdxev/auxiliary/sbom_functions.py
cdxev/auxiliary/schema/__init__.py
cdxev/auxiliary/schema/bom-1.2-strict.schema.json
cdxev/auxiliary/schema/bom-1.2.schema.json
cdxev/auxiliary/schema/bom-1.3-custom.schema.json
cdxev/auxiliary/schema/bom-1.3-strict.schema.json
cdxev/auxiliary/schema/bom-1.3.schema.json
cdxev/auxiliary/schema/bom-1.4-custom.schema.json
cdxev/auxiliary/schema/bom-1.4.schema.json
cdxev/auxiliary/schema/bom-1.5-custom.schema.json
cdxev/auxiliary/schema/bom-1.5.schema.json
cdxev/auxiliary/schema/bom-1.6-custom.schema.json
cdxev/auxiliary/schema/bom-1.6.schema.json
cdxev/auxiliary/schema/jsf-0.82.schema.json
cdxev/auxiliary/schema/spdx.schema.json
cdxev/validator/__init__.py
cdxev/validator/customreports.py
cdxev/validator/helper.py
cdxev/validator/validate.py
cyclonedx_editor_validator-0.30.3.dist-info/METADATA
cyclonedx_editor_validator-0.30.3.dist-info/WHEEL
cyclonedx_editor_validator-0.30.3.dist-info/entry_points.txt
cyclonedx_editor_validator-0.30.3.dist-info/licenses/LICENSE
cyclonedx_editor_validator-0.30.3.dist-info/licenses/NOTICE
cyclonedx_editor_validator-0.30.3.dist-info/RECORD
