Metadata-Version: 2.4
Name: cyclonedx-editor-validator
Version: 0.30.3
Summary: Tool for creating, modifying and validating CycloneDX SBOMs.
Project-URL: Documentation, https://festo-se.github.io/cyclonedx-editor-validator/
Project-URL: Repository, https://github.com/Festo-se/cyclonedx-editor-validator/
Project-URL: Issues, https://github.com/Festo-se/cyclonedx-editor-validator/issues
Project-URL: Changelog, https://github.com/Festo-se/cyclonedx-editor-validator/releases
Author-email: Aleg Vilinski <aleg.vilinski@festo.com>, Christian Beck <christian.beck@festo.com>, Moritz Marseu <moritz.marseu@festo.com>
License-Expression: GPL-3.0-or-later
License-File: LICENSE
License-File: NOTICE
Requires-Python: <4,>=3.10.0
Requires-Dist: charset-normalizer<4,>=3.3.2
Requires-Dist: cyclonedx-python-lib==11.6.0
Requires-Dist: docstring-parser<0.18,>=0.16
Requires-Dist: email-validator==2.3.0
Requires-Dist: jsonschema[format]==4.26.0
Requires-Dist: natsort<9,>=8.4.0
Requires-Dist: pyicu<3,>=2.13.1; sys_platform == 'darwin'
Requires-Dist: pyicu<3,>=2.13.1; sys_platform == 'linux'
Requires-Dist: python-dateutil==2.9.0.post0
Requires-Dist: univers==31.1.0
